redistq/__init__.py
redistq/task_queue.py
redistq/version.py
redis_tq-0.0.11.dist-info/LICENSE
redis_tq-0.0.11.dist-info/METADATA
redis_tq-0.0.11.dist-info/WHEEL
redis_tq-0.0.11.dist-info/top_level.txt
redis_tq-0.0.11.dist-info/RECORD
