Metadata-Version: 2.1
Name: redis-tq
Version: 0.0.11
Summary: Redis Based Task Queue
Home-page: https://github.com/flix-tech/redis-tq
Author: FlixTech
Author-email: open-source@flixbus.com
License: MIT
Project-URL: Changelog, https://github.com/flix-tech/redis-tq/blob/master/CHANGELOG.md
Keywords: redis task queue
Requires-Python: >=3.7
License-File: LICENSE
Requires-Dist: redis
